Workbook

Sheet Leia-me
A1: Calculadora de Impacto da Reforma
A2: Kit Não Vire Estatística · Plano de Blindagem 2027–2030
A4: Para que serve:
A5: • Estimar quanto a troca de PIS/Cofins/ICMS/ISS por CBS/IBS muda o imposto, o lucro e o preço do seu negócio, ano a ano, de 2026 a 2033.
A6: Como usar:
A7: • Aba 1: preencha as células amarelas com números de um mês típico.
A8: • Aba 2: as alíquotas são EDITÁVEIS. Quando o Senado fixar a alíquota oficial da CBS (até 15/12/2026), troque a célula B4. Tudo recalcula.
A9: • Aba 3: veja a carga de impostos ano a ano e o reajuste de preço necessário para manter o lucro de hoje.
A10: • Aba 4 (só Simples): compare ficar 'por dentro' x ir para o regime regular de IBS/CBS ('híbrido').
A11: Funciona no Excel e no Google Planilhas (drive.google.com → Novo → Upload → Abrir com Planilhas Google).
A12: Limites: não simula regimes específicos (combustíveis, financeiro, imóveis, cooperativas, ZFM), substituição tributária nem benefícios de ICMS. Considera que os fornecedores do regime regular repassam IBS/CBS no preço.
A14: Legenda:
... A18: Conteúdo educativo; não substitui contador. Alíquotas de 2027+ são estimativas não oficiais (dados de 28/10/2026).

Sheet 1. Seus dados
A1: 1. Seus dados
A2: Preencha as células amarelas com valores de um MÊS típico
A4: Item | B4: Valor | C4: Ajuda
A5: Faturamento bruto do mês | B5: 40000 | C5: Tudo o que vendeu no mês, com impostos.
A6: Compras com nota fiscal no mês (mercadoria, insumos, serviços, energia, frete) | B6: 18000 | C6: Só compras com nota. Salário não entra.
A7: % dessas compras de fornecedores do regime regular (Presumido/Real ou Simples híbrido) | B7: 0.6 | C7: Compra de MEI, Simples 'por dentro' ou pessoa física gera pouco ou nenhum crédito.
A8: Folha + encargos + pró-labore do mês | B8: 9000 | C8: Não gera crédito de IBS/CBS.
A9: Outras despesas sem nota/sem crédito (aluguel PF, tarifas, etc.) | B9: 4000
A10: Regime tributário atual | B10: Lucro Presumido | C10: Lista: MEI, Simples Nacional, Lucro Presumido, Lucro Real
A11: Impostos sobre a venda HOJE (soma, % do faturamento) | B11: 0.1165 | C11: Presumido: PIS/Cofins 3,65% + ICMS/ISS efetivo. Simples: alíquota efetiva do DAS. Pergunte ao contador.
A12: Desses, quanto é PIS/Cofins (% do faturamento) | B12: 0.0365 | C12: Presumido 3,65%; Real até 9,25%; Simples: parte de PIS/Cofins do DAS.
A13: Crédito de PIS/Cofins que você aproveita hoje (% das compras) | B13: 0 | C13: Presumido: 0. Real: em geral 9,25%.
A14: Crédito de ICMS que você aproveita hoje (% das compras) | B14: 0 | C14: Comércio/indústria no regime normal de ICMS. Serviços e Simples: 0.
A15: Redução de alíquota do seu item principal | B15: 0 | C15: 0% (cheia), 30% (profissões regulamentadas), 60% (saúde, educação, alimentos listados) ou 100% (alíquota zero).
A16: % das vendas para outras empresas | B16: 0.3 | C16: Usado na aba 4.

Sheet 2. Alíquotas
A1: 2. Alíquotas (EDITÁVEIS)
A2: Estimativas não oficiais em 28/10/2026 · troque quando sair a alíquota oficial
A4: CBS (alíquota de referência) | B4: 0.0921 | C4: Estimativa não oficial do Comitê Gestor. Oficial: Senado fixa até 15/12/2026.
A5: IBS no modelo final (estados + municípios) | B5: 0.187 | C5: Estimativa não oficial. Total estimado 27,91%; teto de referência da lei: 26,5% em 2033, com ajuste.
A6: Alíquota total no modelo final | B6: =B4+B5
A8: Ano | B8: CBS | C8: IBS | D8: PIS/Cofins que ainda existe | E8: ICMS/ISS que ainda existe | F8: Observação
A9: 2026 | B9: 0 | C9: 0 | D9: 1 | E9: 1 | F9: Ano de teste: CBS 0,9% e IBS 0,1% só destacados (compensáveis). Mantido 0 aqui.
A10: 2027 | B10: =B4 | C10: 0.001 | D10: 0 | E10: 1 | F10: CBS substitui PIS/Cofins. IBS 0,1%. IPI zera (exceto ZFM).
A11: 2028 | B11: =B4 | C11: 0.001 | D11: 0 | E11: 1 | F11: Igual a 2027.
A12: 2029 | B12: =B4 | C12: =B5*0.1 | D12: 0 | E12: 0.9 | F12: ICMS/ISS a 90%.
A13: 2030 | B13: =B4 | C13: =B5*0.2 | D13: 0 | E13: 0.8 | F13: ICMS/ISS a 80%.
A14: 2031 | B14: =B4 | C14: =B5*0.3 | D14: 0 | E14: 0.7 | F14: ICMS/ISS a 70%.
A15: 2032 | B15: =B4 | C15: =B5*0.4 | D15: 0 | E15: 0.6 | F15: ICMS/ISS a 60%.
A16: 2033 | B16: =B4 | C16: =B5 | D16: 0 | E16: 0 | F16: Modelo completo.
A18: Proporção de IBS de 2029 a 2032: aproximação didática (10%, 20%, 30%, 40% do IBS final). A proporção exata depende da regulamentação. Edite se o seu contador indicar outro valor.

Sheet 3. Resultado
A1: 3. Resultado ano a ano
A2: Regime regular de IBS/CBS (Presumido/Real ou Simples híbrido). Simples 'por dentro': veja a aba 4.
A4: Ano | B4: Alíquota IBS+CBS efetiva | C4: Débito IBS/CBS (por fora) | D4: PIS/Cofins + ICMS/ISS | E4: (−) Créditos | F4: Imposto líquido | G4: Carga sobre o faturamento | H4: Variação x hoje | I4: Lucro do mês (mesmo preço) | J4: Reajuste de preço p/ manter o lucro
A5: Hoje | B5: 0 | C5: 0 | D5: ='1. Seus dados'!B5*'1. Seus dados'!B11 | E5: ='1. Seus dados'!B6*('1. Seus dados'!B13+'1. Seus dados'!B14)*'1. Seus dados'!B7 | F5: =C5+D5-E5 | G5: =F5/'1. Seus dados'!B5 | H5: =0 | I5: ='1. Seus dados'!B5-F5-'1. Seus dados'!B6-'1. Seus dados'!B8-'1. Seus dados'!B9 | J5: 0
A6: ='2. Alíquotas'!A9 | B6: =('2. Alíquotas'!B9+'2. Alíquotas'!C9)*(1-'1. Seus dados'!B15) | C6: ='1. Seus dados'!B5/(1+B6)*B6 | D6: ='1. Seus dados'!B5*('1. Seus dados'!B12*'2. Alíquotas'!D9+('1. Seus dados'!B11-'1. Seus dados'!B12)*'2. Alíquotas'!E9) | E6: ='1. Seus dados'!B6*'1. Seus dados'!B7*(('2. Alíquotas'!B9+'2. Alíquotas'!C9)/(1+'2. Alíquotas'!B9+'2. Alíquotas'!C9)+'1. Seus dados'!B13*'2. Alíquotas'!D9+'1. Seus dados'!B14*'2. Alíquotas'!E9) | F6: =MAX(0,C6+D6-E6) | G6: =F6/'1. Seus dados'!B5 | H6: =G6-$G$5 | I6: ='1. Seus dados'!B5-F6-'1. Seus dados'!B6-'1. Seus dados'!B8-'1. Seus dados'!B9 | J6: =IFERROR(($I$5-I6)/(1/(1+B6)-('1. Seus dados'!B11-'1. Seus dados'!B12)*'2. Alíquotas'!E9)/'1. Seus dados'!B5,0)
A7: ='2. Alíquotas'!A10 | B7: =('2. Alíquotas'!B10+'2. Alíquotas'!C10)*(1-'1. Seus dados'!B15) | C7: ='1. Seus dados'!B5/(1+B7)*B7 | D7: ='1. Seus dados'!B5*('1. Seus dados'!B12*'2. Alíquotas'!D10+('1. Seus dados'!B11-'1. Seus dados'!B12)*'2. Alíquotas'!E10) | E7: ='1. Seus dados'!B6*'1. Seus dados'!B7*(('2. Alíquotas'!B10+'2. Alíquotas'!C10)/(1+'2. Alíquotas'!B10+'2. Alíquotas'!C10)+'1. Seus dados'!B13*'2. Alíquotas'!D10+'1. Seus dados'!B14*'2. Alíquotas'!E10) | F7: =MAX(0,C7+D7-E7) | G7: =F7/'1. Seus dados'!B5 | H7: =G7-$G$5 | I7: ='1. Seus dados'!B5-F7-'1. Seus dados'!B6-'1. Seus dados'!B8-'1. Seus dados'!B9 | J7: =IFERROR(($I$5-I7)/(1/(1+B7)-('1. Seus dados'!B11-'1. Seus dados'!B12)*'2. Alíquotas'!E10)/'1. Seus dados'!B5,0)
A8: ='2. Alíquotas'!A11 | B8: =('2. Alíquotas'!B11+'2. Alíquotas'!C11)*(1-'1. Seus dados'!B15) | C8: ='1. Seus dados'!B5/(1+B8)*B8 | D8: ='1. Seus dados'!B5*('1. Seus dados'!B12*'2. Alíquotas'!D11+('1. Seus dados'!B11-'1. Seus dados'!B12)*'2. Alíquotas'!E11) | E8: ='1. Seus dados'!B6*'1. Seus dados'!B7*(('2. Alíquotas'!B11+'2. Alíquotas'!C11)/(1+'2. Alíquotas'!B11+'2. Alíquotas'!C11)+'1. Seus dados'!B13*'2. Alíquotas'!D11+'1. Seus dados'!B14*'2. Alíquotas'!E11) | F8: =MAX(0,C8+D8-E8) | G8: =F8/'1. Seus dados'!B5 | H8: =G8-$G$5 | I8: ='1. Seus dados'!B5-F8-'1. Seus dados'!B6-'1. Seus dados'!B8-'1. Seus dados'!B9 | J8: =IFERROR(($I$5-I8)/(1/(1+B8)-('1. Seus dados'!B11-'1. Seus dados'!B12)*'2. Alíquotas'!E11)/'1. Seus dados'!B5,0)
A9: ='2. Alíquotas'!A12 | B9: =('2. Alíquotas'!B12+'2. Alíquotas'!C12)*(1-'1. Seus dados'!B15) | C9: ='1. Seus dados'!B5/(1+B9)*B9 | D9: ='1. Seus dados'!B5*('1. Seus dados'!B12*'2. Alíquotas'!D12+('1. Seus dados'!B11-'1. Seus dados'!B12)*'2. Alíquotas'!E12) | E9: ='1. Seus dados'!B6*'1. Seus dados'!B7*(('2. Alíquotas'!B12+'2. Alíquotas'!C12)/(1+'2. Alíquotas'!B12+'2. Alíquotas'!C12)+'1. Seus dados'!B13*'2. Alíquotas'!D12+'1. Seus dados'!B14*'2. Alíquotas'!E12) | F9: =MAX(0,C9+D9-E9) | G9: =F9/'1. Seus dados'!B5 | H9: =G9-$G$5 | I9: ='1. Seus dados'!B5-F9-'1. Seus dados'!B6-'1. Seus dados'!B8-'1. Seus dados'!B9 | J9: =IFERROR(($I$5-I9)/(1/(1+B9)-('1. Seus dados'!B11-'1. Seus dados'!B12)*'2. Alíquotas'!E12)/'1. Seus dados'!B5,0)
A10: ='2. Alíquotas'!A13 | B10: =('2. Alíquotas'!B13+'2. Alíquotas'!C13)*(1-'1. Seus dados'!B15) | C10: ='1. Seus dados'!B5/(1+B10)*B10 | D10: ='1. Seus dados'!B5*('1. Seus dados'!B12*'2. Alíquotas'!D13+('1. Seus dados'!B11-'1. Seus dados'!B12)*'2. Alíquotas'!E13) | E10: ='1. Seus dados'!B6*'1. Seus dados'!B7*(('2. Alíquotas'!B13+'2. Alíquotas'!C13)/(1+'2. Alíquotas'!B13+'2. Alíquotas'!C13)+'1. Seus dados'!B13*'2. Alíquotas'!D13+'1. Seus dados'!B14*'2. Alíquotas'!E13) | F10: =MAX(0,C10+D10-E10) | G10: =F10/'1. Seus dados'!B5 | H10: =G10-$G$5 | I10: ='1. Seus dados'!B5-F10-'1. Seus dados'!B6-'1. Seus dados'!B8-'1. Seus dados'!B9 | J10: =IFERROR(($I$5-I10)/(1/(1+B10)-('1. Seus dados'!B11-'1. Seus dados'!B12)*'2. Alíquotas'!E13)/'1. Seus dados'!B5,0)
A11: ='2. Alíquotas'!A14 | B11: =('2. Alíquotas'!B14+'2. Alíquotas'!C14)*(1-'1. Seus dados'!B15) | C11: ='1. Seus dados'!B5/(1+B11)*B11 | D11: ='1. Seus dados'!B5*('1. Seus dados'!B12*'2. Alíquotas'!D14+('1. Seus dados'!B11-'1. Seus dados'!B12)*'2. Alíquotas'!E14) | E11: ='1. Seus dados'!B6*'1. Seus dados'!B7*(('2. Alíquotas'!B14+'2. Alíquotas'!C14)/(1+'2. Alíquotas'!B14+'2. Alíquotas'!C14)+'1. Seus dados'!B13*'2. Alíquotas'!D14+'1. Seus dados'!B14*'2. Alíquotas'!E14) | F11: =MAX(0,C11+D11-E11) | G11: =F11/'1. Seus dados'!B5 | H11: =G11-$G$5 | I11: ='1. Seus dados'!B5-F11-'1. Seus dados'!B6-'1. Seus dados'!B8-'1. Seus dados'!B9 | J11: =IFERROR(($I$5-I11)/(1/(1+B11)-('1. Seus dados'!B11-'1. Seus dados'!B12)*'2. Alíquotas'!E14)/'1. Seus dados'!B5,0)
A12: ='2. Alíquotas'!A15 | B12: =('2. Alíquotas'!B15+'2. Alíquotas'!C15)*(1-'1. Seus dados'!B15) | C12: ='1. Seus dados'!B5/(1+B12)*B12 | D12: ='1. Seus dados'!B5*('1. Seus dados'!B12*'2. Alíquotas'!D15+('1. Seus dados'!B11-'1. Seus dados'!B12)*'2. Alíquotas'!E15) | E12: ='1. Seus dados'!B6*'1. Seus dados'!B7*(('2. Alíquotas'!B15+'2. Alíquotas'!C15)/(1+'2. Alíquotas'!B15+'2. Alíquotas'!C15)+'1. Seus dados'!B13*'2. Alíquotas'!D15+'1. Seus dados'!B14*'2. Alíquotas'!E15) | F12: =MAX(0,C12+D12-E12) | G12: =F12/'1. Seus dados'!B5 | H12: =G12-$G$5 | I12: ='1. Seus dados'!B5-F12-'1. Seus dados'!B6-'1. Seus dados'!B8-'1. Seus dados'!B9 | J12: =IFERROR(($I$5-I12)/(1/(1+B12)-('1. Seus dados'!B11-'1. Seus dados'!B12)*'2. Alíquotas'!E15)/'1. Seus dados'!B5,0)
A13: ='2. Alíquotas'!A16 | B13: =('2. Alíquotas'!B16+'2. Alíquotas'!C16)*(1-'1. Seus dados'!B15) | C13: ='1. Seus dados'!B5/(1+B13)*B13 | D13: ='1. Seus dados'!B5*('1. Seus dados'!B12*'2. Alíquotas'!D16+('1. Seus dados'!B11-'1. Seus dados'!B12)*'2. Alíquotas'!E16) | E13: ='1. Seus dados'!B6*'1. Seus dados'!B7*(('2. Alíquotas'!B16+'2. Alíquotas'!C16)/(1+'2. Alíquotas'!B16+'2. Alíquotas'!C16)+'1. Seus dados'!B13*'2. Alíquotas'!D16+'1. Seus dados'!B14*'2. Alíquotas'!E16) | F13: =MAX(0,C13+D13-E13) | G13: =F13/'1. Seus dados'!B5 | H13: =G13-$G$5 | I13: ='1. Seus dados'!B5-F13-'1. Seus dados'!B6-'1. Seus dados'!B8-'1. Seus dados'!B9 | J13: =IFERROR(($I$5-I13)/(1/(1+B13)-('1. Seus dados'!B11-'1. Seus dados'!B12)*'2. Alíquotas'!E16)/'1. Seus dados'!B5,0)
A15: Como ler: 'Débito por fora' considera que o seu faturamento atual já inclui o IBS/CBS (mesmo preço). 'Reajuste' é quanto o preço precisa subir (ou pode cair, se negativo) para o lucro do mês ficar igual ao de hoje.
A16: Estimativa educativa. Confirme com o seu contador antes de mudar preços.

Sheet 4. Simples x Híbrido
A1: 4. Simples: por dentro x híbrido
A2: Para empresas do Simples Nacional · referência: modelo final (2033)
A4: Dado | B4: Valor
A5: Faturamento do mês | B5: ='1. Seus dados'!B5
A6: Alíquota efetiva do DAS hoje | B6: 0.08
A7: Parte de IBS/CBS dentro do DAS (% da venda) — peça ao contador | B7: 0.03
A8: % das vendas para empresas | B8: ='1. Seus dados'!B16
A9: Compras com nota de fornecedores do regime regular | B9: ='1. Seus dados'!B6*'1. Seus dados'!B7
A10: Alíquota IBS+CBS (modelo final) | B10: ='2. Alíquotas'!B6*(1-'1. Seus dados'!B15)
A11: Custo extra estimado de contabilidade/sistema no híbrido (mês) | B11: 300
A13: Resultado | B13: Por dentro | C13: Híbrido | D13: Diferença
A14: Imposto do mês (DAS + IBS/CBS − créditos) | B14: =B5*B6 | C14: =B5*(B6-B7)+B5/(1+B10)*B10-B9*B10/(1+B10)+B11 | D14: =C14-B14
A15: Crédito que o cliente empresa aproveita a cada R$ 1.000 | B15: =1000*B7 | C15: =1000/(1+B10)*B10 | D15: =C15-B15
A16: Crédito total gerado aos clientes empresa no mês | B16: =B5*B8*B7 | C16: =B5*B8/(1+B10)*B10 | D16: =C16-B16
A18: Leitura:
A19: =IF(B8<0.2,"Você vende pouco para empresas: ficar POR DENTRO tende a ser mais simples e barato. Confirme com o contador.",IF(D14<=0,"O híbrido sai mais barato no imposto e ainda gera mais crédito ao cliente: vale avaliar com o contador.","O híbrido custa mais imposto por mês (célula D14), mas gera mais crédito aos seus clientes empresa (célula D16). Vale se os clientes PJ pagariam mais ou deixariam de comprar de você por falta de crédito. Decida com o contador."))
A21: Prazos: opção para jan–jun/2027 até 30/10/2026 (cancelamento de 03/11 a 20/12/2026); depois, janelas em março e setembro de cada ano.
