Workbook

Sheet Leia-me
A1: Fluxo de Caixa 13 Semanas + DRE
A2: Kit Não Vire Estatística · Plano de Blindagem 2027–2030
A4: Para que serve:
A5: • Fluxo 13 semanas: enxergar o caixa 3 meses à frente e descobrir com antecedência a semana em que o dinheiro ficaria negativo.
A6: • DRE mensal: saber se a empresa dá lucro de verdade, qual a margem de contribuição e o ponto de equilíbrio.
A7: Como usar:
A8: • Aba Configurar: data de início (uma segunda-feira), saldo inicial e reserva mínima.
A9: • Aba Fluxo 13 semanas: preencha as células amarelas. Toda segunda, troque o previsto pelo realizado.
A10: • Aba DRE mensal: uma coluna por mês.
A11: Funciona no Excel e no Google Planilhas.
A13: Legenda:
A14: Célula amarela = você preenche
... A17: Conteúdo educativo; não substitui contador. Alíquotas de 2027+ são estimativas não oficiais (dados de 28/10/2026).

Sheet Configurar
A1: Configurar
A4: Nome da empresa | B4: Minha Empresa
A5: Segunda-feira de início da semana 1 | B5: 46328
A6: Saldo de caixa inicial (todas as contas da empresa) | B6: 15000
A7: Reserva mínima desejada (1 mês de custo fixo) | B7: 18000

Sheet Fluxo 13 semanas
A1: Fluxo de caixa · 13 semanas
A2: Preencha entradas e saídas previstas. Toda segunda: troque previsto por realizado.
A4: Semana | B4: S1 | C4: S2 | D4: S3 | E4: S4 | F4: S5 | G4: S6 | H4: S7 | I4: S8 | J4: S9 | K4: S10 | L4: S11 | M4: S12 | N4: S13 | O4: Total
A5: Começa em | B5: ='Configurar'!B5+0 | C5: ='Configurar'!B5+7 | D5: ='Configurar'!B5+14 | E5: ='Configurar'!B5+21 | F5: ='Configurar'!B5+28 | G5: ='Configurar'!B5+35 | H5: ='Configurar'!B5+42 | I5: ='Configurar'!B5+49 | J5: ='Configurar'!B5+56 | K5: ='Configurar'!B5+63 | L5: ='Configurar'!B5+70 | M5: ='Configurar'!B5+77 | N5: ='Configurar'!B5+84
A6: ENTRADAS
A7: Vendas à vista / Pix | B7: 0 | C7: 0 | D7: 0 | E7: 0 | F7: 0 | G7: 0 | H7: 0 | I7: 0 | J7: 0 | K7: 0 | L7: 0 | M7: 0 | N7: 0 | O7: =SUM(B7:N7)
A8: Cartão (o que cai na conta) | B8: 0 | C8: 0 | D8: 0 | E8: 0 | F8: 0 | G8: 0 | H8: 0 | I8: 0 | J8: 0 | K8: 0 | L8: 0 | M8: 0 | N8: 0 | O8: =SUM(B8:N8)
A9: Boletos / duplicatas a receber | B9: 0 | C9: 0 | D9: 0 | E9: 0 | F9: 0 | G9: 0 | H9: 0 | I9: 0 | J9: 0 | K9: 0 | L9: 0 | M9: 0 | N9: 0 | O9: =SUM(B9:N9)
A10: Outras entradas | B10: 0 | C10: 0 | D10: 0 | E10: 0 | F10: 0 | G10: 0 | H10: 0 | I10: 0 | J10: 0 | K10: 0 | L10: 0 | M10: 0 | N10: 0 | O10: =SUM(B10:N10)
A11: Total de entradas | B11: =SUM(B7:B10) | C11: =SUM(C7:C10) | D11: =SUM(D7:D10) | E11: =SUM(E7:E10) | F11: =SUM(F7:F10) | G11: =SUM(G7:G10) | H11: =SUM(H7:H10) | I11: =SUM(I7:I10) | ... O11: =SUM(O7:O10)
A12: SAÍDAS
A13: Fornecedores / mercadoria | B13: 0 | C13: 0 | D13: 0 | E13: 0 | F13: 0 | G13: 0 | H13: 0 | I13: 0 | J13: 0 | K13: 0 | L13: 0 | M13: 0 | N13: 0 | O13: =SUM(B13:N13)
A14: Folha + encargos | B14: 0 | C14: 0 | D14: 0 | E14: 0 | F14: 0 | G14: 0 | H14: 0 | I14: 0 | J14: 0 | K14: 0 | L14: 0 | M14: 0 | N14: 0 | O14: =SUM(B14:N14)
A15: Pró-labore | B15: 0 | C15: 0 | D15: 0 | E15: 0 | F15: 0 | G15: 0 | H15: 0 | I15: 0 | J15: 0 | K15: 0 | L15: 0 | M15: 0 | N15: 0 | O15: =SUM(B15:N15)
A16: Aluguel e condomínio | B16: 0 | C16: 0 | D16: 0 | E16: 0 | F16: 0 | G16: 0 | H16: 0 | I16: 0 | J16: 0 | K16: 0 | L16: 0 | M16: 0 | N16: 0 | O16: =SUM(B16:N16)
A17: Água, luz, internet, sistemas | B17: 0 | C17: 0 | D17: 0 | E17: 0 | F17: 0 | G17: 0 | H17: 0 | I17: 0 | J17: 0 | K17: 0 | L17: 0 | M17: 0 | N17: 0 | O17: =SUM(B17:N17)
A18: Impostos (DAS, guias) | B18: 0 | C18: 0 | D18: 0 | E18: 0 | F18: 0 | G18: 0 | H18: 0 | I18: 0 | J18: 0 | K18: 0 | L18: 0 | M18: 0 | N18: 0 | O18: =SUM(B18:N18)
A19: Parcelas de empréstimos | B19: 0 | C19: 0 | D19: 0 | E19: 0 | F19: 0 | G19: 0 | H19: 0 | I19: 0 | J19: 0 | K19: 0 | L19: 0 | M19: 0 | N19: 0 | O19: =SUM(B19:N19)
A20: Marketing | B20: 0 | C20: 0 | D20: 0 | E20: 0 | F20: 0 | G20: 0 | H20: 0 | I20: 0 | J20: 0 | K20: 0 | L20: 0 | M20: 0 | N20: 0 | O20: =SUM(B20:N20)
A21: Outras saídas | B21: 0 | C21: 0 | D21: 0 | E21: 0 | F21: 0 | G21: 0 | H21: 0 | I21: 0 | J21: 0 | K21: 0 | L21: 0 | M21: 0 | N21: 0 | O21: =SUM(B21:N21)
A22: Total de saídas | B22: =SUM(B13:B21) | C22: =SUM(C13:C21) | D22: =SUM(D13:D21) | E22: =SUM(E13:E21) | F22: =SUM(F13:F21) | G22: =SUM(G13:G21) | H22: =SUM(H13:H21) | I22: =SUM(I13:I21) | ... O22: =SUM(O13:O21)
A24: Saldo inicial da semana | B24: ='Configurar'!B6 | C24: =B26 | D24: =C26 | E24: =D26 | F24: =E26 | G24: =F26 | H24: =G26 | I24: =H26 | J24: =I26 | ... N24: =M26
A25: Resultado da semana | B25: =B11-B22 | C25: =C11-C22 | D25: =D11-D22 | E25: =E11-E22 | F25: =F11-F22 | G25: =G11-G22 | H25: =H11-H22 | I25: =I11-I22 | ... N25: =N11-N22
A26: SALDO FINAL | B26: =B24+B25 | C26: =C24+C25 | D26: =D24+D25 | E26: =E24+E25 | F26: =F24+F25 | G26: =G24+G25 | H26: =H24+H25 | I26: =I24+I25 | ... N26: =N24+N25
A27: Acima da reserva mínima? | B27: =IF(B26<0,"NEGATIVO",IF(B26<'Configurar'!B7,"Abaixo","OK")) | C27: =IF(C26<0,"NEGATIVO",IF(C26<'Configurar'!B7,"Abaixo","OK")) | D27: =IF(D26<0,"NEGATIVO",IF(D26<'Configurar'!B7,"Abaixo","OK")) | E27: =IF(E26<0,"NEGATIVO",IF(E26<'Configurar'!B7,"Abaixo","OK")) | F27: =IF(F26<0,"NEGATIVO",IF(F26<'Configurar'!B7,"Abaixo","OK")) | G27: =IF(G26<0,"NEGATIVO",IF(G26<'Configurar'!B7,"Abaixo","OK")) | H27: =IF(H26<0,"NEGATIVO",IF(H26<'Configurar'!B7,"Abaixo","OK")) | I27: =IF(I26<0,"NEGATIVO",IF(I26<'Configurar'!B7,"Abaixo","OK")) | J27: =IF(J26<0,"NEGATIVO",IF(J26<'Configurar'!B7,"Abaixo","OK")) | K27: =IF(K26<0,"NEGATIVO",IF(K26<'Configurar'!B7,"Abaixo","OK")) | L27: =IF(L26<0,"NEGATIVO",IF(L26<'Configurar'!B7,"Abaixo","OK")) | M27: =IF(M26<0,"NEGATIVO",IF(M26<'Configurar'!B7,"Abaixo","OK")) | N27: =IF(N26<0,"NEGATIVO",IF(N26<'Configurar'!B7,"Abaixo","OK"))
A29: Menor saldo previsto | B29: =MIN(B26:N26)
A30: Primeira semana negativa | B30: =IFERROR("S"&MATCH(TRUE,INDEX(B26:N26<0,0),0),"Nenhuma")

Sheet DRE mensal
A1: DRE simples · mês a mês
A2: Regime de competência: o que foi vendido e gasto no mês
A4: Linha | B4: Jan | C4: Fev | D4: Mar | E4: Abr | F4: Mai | G4: Jun | H4: Jul | I4: Ago | J4: Set | K4: Out | L4: Nov | M4: Dez | N4: Ano
A5: (+) Faturamento bruto | B5: 0 | C5: 0 | D5: 0 | E5: 0 | F5: 0 | G5: 0 | H5: 0 | I5: 0 | J5: 0 | K5: 0 | L5: 0 | M5: 0 | N5: =SUM(B5:M5)
A6: (−) Impostos sobre a venda | B6: 0 | C6: 0 | D6: 0 | E6: 0 | F6: 0 | G6: 0 | H6: 0 | I6: 0 | J6: 0 | K6: 0 | L6: 0 | M6: 0 | N6: =SUM(B6:M6)
A7: (=) Receita líquida | B7: =B5-B6 | C7: =C5-C6 | D7: =D5-D6 | E7: =E5-E6 | F7: =F5-F6 | G7: =G5-G6 | H7: =H5-H6 | I7: =I5-I6 | ... M7: =M5-M6 | N7: =SUM(B7:M7)
A8: (−) Custo da mercadoria / insumos / serviço | B8: 0 | C8: 0 | D8: 0 | E8: 0 | F8: 0 | G8: 0 | H8: 0 | I8: 0 | J8: 0 | K8: 0 | L8: 0 | M8: 0 | N8: =SUM(B8:M8)
A9: (−) Taxas de cartão, comissões, fretes de venda | B9: 0 | C9: 0 | D9: 0 | E9: 0 | F9: 0 | G9: 0 | H9: 0 | I9: 0 | J9: 0 | K9: 0 | L9: 0 | M9: 0 | N9: =SUM(B9:M9)
A10: (=) Margem de contribuição | B10: =B7-B8-B9 | C10: =C7-C8-C9 | D10: =D7-D8-D9 | E10: =E7-E8-E9 | F10: =F7-F8-F9 | G10: =G7-G8-G9 | H10: =H7-H8-H9 | I10: =I7-I8-I9 | ... M10: =M7-M8-M9 | N10: =SUM(B10:M10)
A11: Margem de contribuição % | B11: =IFERROR(B10/B5,0) | C11: =IFERROR(C10/C5,0) | D11: =IFERROR(D10/D5,0) | E11: =IFERROR(E10/E5,0) | F11: =IFERROR(F10/F5,0) | G11: =IFERROR(G10/G5,0) | H11: =IFERROR(H10/H5,0) | I11: =IFERROR(I10/I5,0) | ... N11: =IFERROR(N10/N5,0)
A12: (−) Folha + encargos | B12: 0 | C12: 0 | D12: 0 | E12: 0 | F12: 0 | G12: 0 | H12: 0 | I12: 0 | J12: 0 | K12: 0 | L12: 0 | M12: 0 | N12: =SUM(B12:M12)
A13: (−) Pró-labore | B13: 0 | C13: 0 | D13: 0 | E13: 0 | F13: 0 | G13: 0 | H13: 0 | I13: 0 | J13: 0 | K13: 0 | L13: 0 | M13: 0 | N13: =SUM(B13:M13)
A14: (−) Aluguel, contas, sistemas | B14: 0 | C14: 0 | D14: 0 | E14: 0 | F14: 0 | G14: 0 | H14: 0 | I14: 0 | J14: 0 | K14: 0 | L14: 0 | M14: 0 | N14: =SUM(B14:M14)
A15: (−) Outras despesas fixas | B15: 0 | C15: 0 | D15: 0 | E15: 0 | F15: 0 | G15: 0 | H15: 0 | I15: 0 | J15: 0 | K15: 0 | L15: 0 | M15: 0 | N15: =SUM(B15:M15)
A16: (=) Total de despesas fixas | B16: =SUM(B12:B15) | C16: =SUM(C12:C15) | D16: =SUM(D12:D15) | E16: =SUM(E12:E15) | F16: =SUM(F12:F15) | G16: =SUM(G12:G15) | H16: =SUM(H12:H15) | I16: =SUM(I12:I15) | ... M16: =SUM(M12:M15) | N16: =SUM(B16:M16)
A17: (=) Resultado operacional | B17: =B10-B16 | C17: =C10-C16 | D17: =D10-D16 | E17: =E10-E16 | F17: =F10-F16 | G17: =G10-G16 | H17: =H10-H16 | I17: =I10-I16 | ... M17: =M10-M16 | N17: =SUM(B17:M17)
A18: (−) Juros e parcelas de empréstimos (juros) | B18: 0 | C18: 0 | D18: 0 | E18: 0 | F18: 0 | G18: 0 | H18: 0 | I18: 0 | J18: 0 | K18: 0 | L18: 0 | M18: 0 | N18: =SUM(B18:M18)
A19: (=) LUCRO LÍQUIDO | B19: =B17-B18 | C19: =C17-C18 | D19: =D17-D18 | E19: =E17-E18 | F19: =F17-F18 | G19: =G17-G18 | H19: =H17-H18 | I19: =I17-I18 | ... M19: =M17-M18 | N19: =SUM(B19:M19)
A20: Lucro líquido % | B20: =IFERROR(B19/B5,0) | C20: =IFERROR(C19/C5,0) | D20: =IFERROR(D19/D5,0) | E20: =IFERROR(E19/E5,0) | F20: =IFERROR(F19/F5,0) | G20: =IFERROR(G19/G5,0) | H20: =IFERROR(H19/H5,0) | I20: =IFERROR(I19/I5,0) | ... N20: =IFERROR(N19/N5,0)
A21: Ponto de equilíbrio (faturamento) | B21: =IFERROR((B16+B18)/B11,0) | C21: =IFERROR((C16+C18)/C11,0) | D21: =IFERROR((D16+D18)/D11,0) | E21: =IFERROR((E16+E18)/E11,0) | F21: =IFERROR((F16+F18)/F11,0) | G21: =IFERROR((G16+G18)/G11,0) | H21: =IFERROR((H16+H18)/H11,0) | I21: =IFERROR((I16+I18)/I11,0) | ... N21: =IFERROR((N16+N18)/N11,0)
