Workbook

Sheet Início
A1: Painel de Implementação 2027
A2: Kit Implementação 2027 · Kit Não Vire Estatística
A4: Empresa | B4: Minha Empresa
A5: Segmento | B5: Comércio e Alimentação
A6: Data de início do plano | B6: 46328
A7: Saldo de caixa inicial | B7: 15000
A8: Reserva mínima (1 mês de custo fixo) | B8: 18000
A10: Resumo | B10: Valor
A11: Tarefas do plano concluídas | B11: =COUNTIF('Plano 30 dias'!F5:F34,"OK")&" de 30"
A12: Progresso do plano | B12: =COUNTIF('Plano 30 dias'!F5:F34,"OK")/30
A13: Última nota do diagnóstico | B13: =IFERROR(LOOKUP(2,1/('Nota mês a mês'!B5:B28<>""),'Nota mês a mês'!B5:B28),"—")
A14: Menor saldo previsto em 13 semanas | B14: ='Caixa semanal'!B29
A15: Primeira semana negativa | B15: ='Caixa semanal'!B30
A16: Próxima data da reforma | B16: =IFERROR(INDEX(Calendário!B5:B16,MATCH(TRUE,INDEX(Calendário!A5:A16>=TODAY(),0),0)),"—")
A17: Faltam (dias) | B17: =IFERROR(INDEX(Calendário!A5:A16,MATCH(TRUE,INDEX(Calendário!A5:A16>=TODAY(),0),0))-TODAY(),"—")

Sheet Plano 30 dias
A1: Plano 30 dias
A2: Marque OK na coluna Status. As datas saem da aba Início.
A4: Dia | B4: Data | C4: Escudo | D4: Tarefa | E4: Como fazer | F4: Status
A5: 1 | B5: =Início!$B$6+0 | C5: Caixa | D5: Separe o dinheiro da empresa do seu | E5: Abra (ou confirme) uma conta só da empresa. Defina hoje o seu pró-labore fixo do mês e pare de pagar contas pessoais pela empresa.
A6: 2 | B6: =Início!$B$6+1 | C6: Caixa | D6: Liste tudo o que você tem para pagar | E6: Todas as contas das próximas 13 semanas: fornecedores, folha, aluguel, impostos, parcelas. Coloque data e valor. Use a planilha de 13 semanas ou o bloco de notas.
A7: 3 | B7: =Início!$B$6+2 | C7: Caixa | D7: Liste tudo o que você tem a receber | E7: Quem deve, quanto, e há quantos dias venceu. Separe: a vencer, até 30 dias de atraso, mais de 30 dias.
A8: 4 | B8: =Início!$B$6+3 | C8: Caixa | D8: Calcule o seu fôlego | E8: Use a calculadora de fôlego com os números reais e o cenário de vendas 20% menores. Anote quantos meses o caixa aguenta.
A9: 5 | B9: =Início!$B$6+4 | C9: Caixa | D9: Corte ou renegocie 3 custos fixos | E9: Assinaturas que ninguém usa, plano de telefone/internet, aluguel de máquina, contrato de sistema. Ligue e peça desconto ou cancele.
A10: 6 | B10: =Início!$B$6+5 | C10: Caixa | D10: Cobre os atrasados (régua de cobrança) | E10: Envie as mensagens da régua para todos os clientes com atraso, começando pelos maiores valores. Ofereça Pix à vista ou 2 vezes.
A11: 7 | B11: =Início!$B$6+6 | C11: Caixa | D11: Revisão da semana 1 | E11: Atualize o fluxo de 13 semanas, marque o que foi feito e anote quanto entrou de cobrança. Defina a % das vendas que vai para a reserva (comece com 3% a 5%).
A12: 8 | B12: =Início!$B$6+7 | C12: Margem | D12: Seus 10 campeões de venda | E12: Liste os 10 produtos ou serviços que mais vendem, com preço e custo direto de cada um.
A13: 9 | B13: =Início!$B$6+8 | C13: Margem | D13: Calcule a margem de cada um | E13: Margem = preço − imposto − custo direto − taxa de cartão/app. Marque em vermelho quem tem margem abaixo de 20%.
A14: 10 | B14: =Início!$B$6+9 | C14: Margem | D14: Descubra o seu ponto de equilíbrio | E14: Use a calculadora de fôlego: ela mostra quanto precisa vender por mês para empatar. Divida pelos dias de trabalho e tenha a meta diária.
A15: 11 | B15: =Início!$B$6+10 | C15: Margem | D15: Simule o preço para 2027 | E15: No simulador, rode os 3 itens mais importantes com a regra nova. Anote se o preço precisa subir, ficar ou pode cair.
A16: 12 | B16: =Início!$B$6+11 | C16: Margem | D16: A: Transforme estoque parado em caixa | B: Meça a sua hora real | C: Calcule o seu ciclo financeiro | E16: Comércio: Liste o que está parado há mais de 90 dias e crie uma ação de giro: combo, kit, queima com prazo ou troca com o fornecedor. | Serviços: Anote por 1 semana as horas faturadas e não faturadas. Preço da hora = (custos do mês + pró-labore + lucro desejado) ÷ horas faturáveis. | Indústria/B2B: Ciclo = dias para receber + dias de estoque − dias para pagar. Cada dia a menos libera caixa. Anote o seu número.
A17: 13 | B17: =Início!$B$6+12 | C17: Margem | D17: Crie a regra do parcelamento | E17: Defina: desconto para Pix à vista, até quantas vezes sem juros e a partir de quando cobra juros. Use a calculadora de custo da venda a prazo.
A18: 14 | B18: =Início!$B$6+13 | C18: Margem | D18: Revisão da semana 2 | E18: Reajuste o que estava com prejuízo, comunique o cliente com antecedência e atualize o fluxo de caixa.
A19: 15 | B19: =Início!$B$6+14 | C19: Caixa | D19: Coloque todas as dívidas na mesa | E19: No comparador de dívidas, lance cada empréstimo, cartão, cheque especial e parcelamento com a taxa ao mês.
A20: 16 | B20: =Início!$B$6+15 | C20: Caixa | D20: Descubra qual dívida está te sangrando | E20: O comparador ordena da mais cara para a mais barata e compara com a Selic. A primeira da lista é a que você ataca.
A21: 17 | B21: =Início!$B$6+16 | C21: Caixa | D21: Renegocie a dívida mais cara | E21: Ligue ou vá ao banco com o roteiro: peça troca por linha mais barata, carência ou alongamento. Peça a proposta por escrito com o CET.
A22: 18 | B22: =Início!$B$6+17 | C22: Caixa | D22: Pesquise linhas de crédito mais baratas | E22: Pergunte no seu banco e em cooperativas pelo Pronampe (teto de Selic + 6% ao ano) e por linhas com garantia do FGO/FAMPE. Só use para trocar dívida cara ou para algo que dá retorno.
A23: 19 | B23: =Início!$B$6+18 | C23: Caixa | D23: Ganhe prazo dos fornecedores | E23: Peça +15 dias de prazo aos 3 maiores fornecedores, oferecendo fidelidade ou volume. Prazo de fornecedor é o crédito mais barato que existe.
A24: 20 | B24: =Início!$B$6+19 | C24: Caixa | D24: Programe a reserva mínima | E24: Crie uma conta/caixinha separada e programe a transferência diária ou semanal da % definida. Meta: 1 mês de custo fixo; depois 3 meses.
A25: 21 | B25: =Início!$B$6+20 | C25: Caixa | D25: Revisão da semana 3 | E25: Quanto você economizou de juros? Atualize o fluxo de 13 semanas e o fôlego.
A26: 22 | B26: =Início!$B$6+21 | C26: Fiscal | D26: Descubra quanto você paga de imposto | E26: Peça ao contador a alíquota efetiva dos últimos 12 meses e confirme o seu regime.
A27: 23 | B27: =Início!$B$6+22 | C27: Fiscal | D27: Faça o checklist da reforma | E27: Marque no painel o que já está feito e o que falta. O que faltar vira pergunta para o contador.
A28: 24 | B28: =Início!$B$6+23 | C28: Fiscal | D28: Confira o seu sistema de notas | E28: Pergunte ao fornecedor do sistema/PDV se a nota já sai com CBS e IBS e se está pronto para 2027.
A29: 25 | B29: =Início!$B$6+24 | C29: Fiscal | D29: Reunião com o contador | E29: Leve as 12 perguntas do roteiro (no painel) e anote as respostas. Peça a simulação de 2027 por escrito.
A30: 26 | B30: =Início!$B$6+25 | C30: Fiscal | D30: A: Atualize a tabela de preços para 2027 | B: Coloque a cláusula tributária no contrato | C: Faça o aditivo tributário nos contratos | E30: Comércio: Com o simulador e a conversa com o contador, prepare a tabela de janeiro de 2027 e o aviso aos clientes. | Serviços: Use o modelo da biblioteca e peça ao seu advogado para revisar. Aplique nos contratos novos e nas renovações. | Indústria/B2B: Use o modelo de aditivo da biblioteca, revise com o advogado e envie aos clientes com contrato longo.
A31: 27 | B31: =Início!$B$6+26 | C31: Fiscal | D31: Decida o caminho do Simples (se for o seu caso) | E31: Com a simulação do contador, decida: por dentro ou híbrido. A próxima janela é março de 2027 (efeito no 2º semestre).
A32: 28 | B32: =Início!$B$6+27 | C32: Fiscal | D32: Marque as datas no calendário | E32: 15/12/2026 (alíquota oficial da CBS), 01/01/2027 (CBS começa), março/2027 (janela do Simples), 2º semestre/2027 (split payment).
A33: 29 | B33: =Início!$B$6+28 | C33: Caixa | D33: Refaça o diagnóstico | E33: Responda de novo as 20 perguntas e compare a nota com a do dia 1. A nota fica salva mês a mês.
A34: 30 | B34: =Início!$B$6+29 | C34: Caixa | D34: Planeje os próximos 60 dias | E34: Veja as metas das semanas 5 a 13 aqui no plano e escolha 1 hábito semanal fixo: toda segunda, atualizar o caixa e cobrar.

Sheet Caixa semanal
A1: Fluxo de caixa · 13 semanas
A2: Preencha entradas e saídas previstas. Toda segunda: troque previsto por realizado.
A4: Semana | B4: S1 | C4: S2 | D4: S3 | E4: S4 | F4: S5 | G4: S6 | H4: S7 | I4: S8 | J4: S9 | K4: S10 | L4: S11 | M4: S12 | N4: S13 | O4: Total
A5: Começa em | B5: =Início!B6+0 | C5: =Início!B6+7 | D5: =Início!B6+14 | E5: =Início!B6+21 | F5: =Início!B6+28 | G5: =Início!B6+35 | H5: =Início!B6+42 | I5: =Início!B6+49 | J5: =Início!B6+56 | K5: =Início!B6+63 | L5: =Início!B6+70 | M5: =Início!B6+77 | N5: =Início!B6+84
A6: ENTRADAS
A7: Vendas à vista / Pix | B7: 0 | C7: 0 | D7: 0 | E7: 0 | F7: 0 | G7: 0 | H7: 0 | I7: 0 | J7: 0 | K7: 0 | L7: 0 | M7: 0 | N7: 0 | O7: =SUM(B7:N7)
A8: Cartão (o que cai na conta) | B8: 0 | C8: 0 | D8: 0 | E8: 0 | F8: 0 | G8: 0 | H8: 0 | I8: 0 | J8: 0 | K8: 0 | L8: 0 | M8: 0 | N8: 0 | O8: =SUM(B8:N8)
A9: Boletos / duplicatas a receber | B9: 0 | C9: 0 | D9: 0 | E9: 0 | F9: 0 | G9: 0 | H9: 0 | I9: 0 | J9: 0 | K9: 0 | L9: 0 | M9: 0 | N9: 0 | O9: =SUM(B9:N9)
A10: Outras entradas | B10: 0 | C10: 0 | D10: 0 | E10: 0 | F10: 0 | G10: 0 | H10: 0 | I10: 0 | J10: 0 | K10: 0 | L10: 0 | M10: 0 | N10: 0 | O10: =SUM(B10:N10)
A11: Total de entradas | B11: =SUM(B7:B10) | C11: =SUM(C7:C10) | D11: =SUM(D7:D10) | E11: =SUM(E7:E10) | F11: =SUM(F7:F10) | G11: =SUM(G7:G10) | H11: =SUM(H7:H10) | I11: =SUM(I7:I10) | ... O11: =SUM(O7:O10)
A12: SAÍDAS
A13: Fornecedores / mercadoria | B13: 0 | C13: 0 | D13: 0 | E13: 0 | F13: 0 | G13: 0 | H13: 0 | I13: 0 | J13: 0 | K13: 0 | L13: 0 | M13: 0 | N13: 0 | O13: =SUM(B13:N13)
A14: Folha + encargos | B14: 0 | C14: 0 | D14: 0 | E14: 0 | F14: 0 | G14: 0 | H14: 0 | I14: 0 | J14: 0 | K14: 0 | L14: 0 | M14: 0 | N14: 0 | O14: =SUM(B14:N14)
A15: Pró-labore | B15: 0 | C15: 0 | D15: 0 | E15: 0 | F15: 0 | G15: 0 | H15: 0 | I15: 0 | J15: 0 | K15: 0 | L15: 0 | M15: 0 | N15: 0 | O15: =SUM(B15:N15)
A16: Aluguel e condomínio | B16: 0 | C16: 0 | D16: 0 | E16: 0 | F16: 0 | G16: 0 | H16: 0 | I16: 0 | J16: 0 | K16: 0 | L16: 0 | M16: 0 | N16: 0 | O16: =SUM(B16:N16)
A17: Água, luz, internet, sistemas | B17: 0 | C17: 0 | D17: 0 | E17: 0 | F17: 0 | G17: 0 | H17: 0 | I17: 0 | J17: 0 | K17: 0 | L17: 0 | M17: 0 | N17: 0 | O17: =SUM(B17:N17)
A18: Impostos (DAS, guias) | B18: 0 | C18: 0 | D18: 0 | E18: 0 | F18: 0 | G18: 0 | H18: 0 | I18: 0 | J18: 0 | K18: 0 | L18: 0 | M18: 0 | N18: 0 | O18: =SUM(B18:N18)
A19: Parcelas de empréstimos | B19: 0 | C19: 0 | D19: 0 | E19: 0 | F19: 0 | G19: 0 | H19: 0 | I19: 0 | J19: 0 | K19: 0 | L19: 0 | M19: 0 | N19: 0 | O19: =SUM(B19:N19)
A20: Marketing | B20: 0 | C20: 0 | D20: 0 | E20: 0 | F20: 0 | G20: 0 | H20: 0 | I20: 0 | J20: 0 | K20: 0 | L20: 0 | M20: 0 | N20: 0 | O20: =SUM(B20:N20)
A21: Outras saídas | B21: 0 | C21: 0 | D21: 0 | E21: 0 | F21: 0 | G21: 0 | H21: 0 | I21: 0 | J21: 0 | K21: 0 | L21: 0 | M21: 0 | N21: 0 | O21: =SUM(B21:N21)
A22: Total de saídas | B22: =SUM(B13:B21) | C22: =SUM(C13:C21) | D22: =SUM(D13:D21) | E22: =SUM(E13:E21) | F22: =SUM(F13:F21) | G22: =SUM(G13:G21) | H22: =SUM(H13:H21) | I22: =SUM(I13:I21) | ... O22: =SUM(O13:O21)
A24: Saldo inicial da semana | B24: =Início!B7 | C24: =B26 | D24: =C26 | E24: =D26 | F24: =E26 | G24: =F26 | H24: =G26 | I24: =H26 | J24: =I26 | ... N24: =M26
A25: Resultado da semana | B25: =B11-B22 | C25: =C11-C22 | D25: =D11-D22 | E25: =E11-E22 | F25: =F11-F22 | G25: =G11-G22 | H25: =H11-H22 | I25: =I11-I22 | ... N25: =N11-N22
A26: SALDO FINAL | B26: =B24+B25 | C26: =C24+C25 | D26: =D24+D25 | E26: =E24+E25 | F26: =F24+F25 | G26: =G24+G25 | H26: =H24+H25 | I26: =I24+I25 | ... N26: =N24+N25
A27: Acima da reserva mínima? | B27: =IF(B26<0,"NEGATIVO",IF(B26<Início!B8,"Abaixo","OK")) | C27: =IF(C26<0,"NEGATIVO",IF(C26<Início!B8,"Abaixo","OK")) | D27: =IF(D26<0,"NEGATIVO",IF(D26<Início!B8,"Abaixo","OK")) | E27: =IF(E26<0,"NEGATIVO",IF(E26<Início!B8,"Abaixo","OK")) | F27: =IF(F26<0,"NEGATIVO",IF(F26<Início!B8,"Abaixo","OK")) | G27: =IF(G26<0,"NEGATIVO",IF(G26<Início!B8,"Abaixo","OK")) | H27: =IF(H26<0,"NEGATIVO",IF(H26<Início!B8,"Abaixo","OK")) | I27: =IF(I26<0,"NEGATIVO",IF(I26<Início!B8,"Abaixo","OK")) | J27: =IF(J26<0,"NEGATIVO",IF(J26<Início!B8,"Abaixo","OK")) | K27: =IF(K26<0,"NEGATIVO",IF(K26<Início!B8,"Abaixo","OK")) | L27: =IF(L26<0,"NEGATIVO",IF(L26<Início!B8,"Abaixo","OK")) | M27: =IF(M26<0,"NEGATIVO",IF(M26<Início!B8,"Abaixo","OK")) | N27: =IF(N26<0,"NEGATIVO",IF(N26<Início!B8,"Abaixo","OK"))
A29: Menor saldo previsto | B29: =MIN(B26:N26)
A30: Primeira semana negativa | B30: =IFERROR("S"&MATCH(TRUE,INDEX(B26:N26<0,0),0),"Nenhuma")

Sheet Nota mês a mês
A1: Nota mês a mês
A2: Refaça o diagnóstico no app 1 vez por mês e copie as notas
A4: Mês | B4: Nota (0–100) | C4: Caixa % | D4: Margem % | E4: Fiscal % | F4: Faixa
A5: =DATE(YEAR(Início!$B$6),MONTH(Início!$B$6)+0,1) | F5: =IF(B5="","",IF(B5<40,"Zona de risco",IF(B5<70,"Atenção","Blindado em construção")))
A6: =DATE(YEAR(Início!$B$6),MONTH(Início!$B$6)+1,1) | F6: =IF(B6="","",IF(B6<40,"Zona de risco",IF(B6<70,"Atenção","Blindado em construção")))
A7: =DATE(YEAR(Início!$B$6),MONTH(Início!$B$6)+2,1) | F7: =IF(B7="","",IF(B7<40,"Zona de risco",IF(B7<70,"Atenção","Blindado em construção")))
A8: =DATE(YEAR(Início!$B$6),MONTH(Início!$B$6)+3,1) | F8: =IF(B8="","",IF(B8<40,"Zona de risco",IF(B8<70,"Atenção","Blindado em construção")))
A9: =DATE(YEAR(Início!$B$6),MONTH(Início!$B$6)+4,1) | F9: =IF(B9="","",IF(B9<40,"Zona de risco",IF(B9<70,"Atenção","Blindado em construção")))
A10: =DATE(YEAR(Início!$B$6),MONTH(Início!$B$6)+5,1) | F10: =IF(B10="","",IF(B10<40,"Zona de risco",IF(B10<70,"Atenção","Blindado em construção")))
A11: =DATE(YEAR(Início!$B$6),MONTH(Início!$B$6)+6,1) | F11: =IF(B11="","",IF(B11<40,"Zona de risco",IF(B11<70,"Atenção","Blindado em construção")))
A12: =DATE(YEAR(Início!$B$6),MONTH(Início!$B$6)+7,1) | F12: =IF(B12="","",IF(B12<40,"Zona de risco",IF(B12<70,"Atenção","Blindado em construção")))
A13: =DATE(YEAR(Início!$B$6),MONTH(Início!$B$6)+8,1) | F13: =IF(B13="","",IF(B13<40,"Zona de risco",IF(B13<70,"Atenção","Blindado em construção")))
A14: =DATE(YEAR(Início!$B$6),MONTH(Início!$B$6)+9,1) | F14: =IF(B14="","",IF(B14<40,"Zona de risco",IF(B14<70,"Atenção","Blindado em construção")))
A15: =DATE(YEAR(Início!$B$6),MONTH(Início!$B$6)+10,1) | F15: =IF(B15="","",IF(B15<40,"Zona de risco",IF(B15<70,"Atenção","Blindado em construção")))
A16: =DATE(YEAR(Início!$B$6),MONTH(Início!$B$6)+11,1) | F16: =IF(B16="","",IF(B16<40,"Zona de risco",IF(B16<70,"Atenção","Blindado em construção")))
A17: =DATE(YEAR(Início!$B$6),MONTH(Início!$B$6)+12,1) | F17: =IF(B17="","",IF(B17<40,"Zona de risco",IF(B17<70,"Atenção","Blindado em construção")))
A18: =DATE(YEAR(Início!$B$6),MONTH(Início!$B$6)+13,1) | F18: =IF(B18="","",IF(B18<40,"Zona de risco",IF(B18<70,"Atenção","Blindado em construção")))
A19: =DATE(YEAR(Início!$B$6),MONTH(Início!$B$6)+14,1) | F19: =IF(B19="","",IF(B19<40,"Zona de risco",IF(B19<70,"Atenção","Blindado em construção")))
A20: =DATE(YEAR(Início!$B$6),MONTH(Início!$B$6)+15,1) | F20: =IF(B20="","",IF(B20<40,"Zona de risco",IF(B20<70,"Atenção","Blindado em construção")))
A21: =DATE(YEAR(Início!$B$6),MONTH(Início!$B$6)+16,1) | F21: =IF(B21="","",IF(B21<40,"Zona de risco",IF(B21<70,"Atenção","Blindado em construção")))
A22: =DATE(YEAR(Início!$B$6),MONTH(Início!$B$6)+17,1) | F22: =IF(B22="","",IF(B22<40,"Zona de risco",IF(B22<70,"Atenção","Blindado em construção")))
A23: =DATE(YEAR(Início!$B$6),MONTH(Início!$B$6)+18,1) | F23: =IF(B23="","",IF(B23<40,"Zona de risco",IF(B23<70,"Atenção","Blindado em construção")))
A24: =DATE(YEAR(Início!$B$6),MONTH(Início!$B$6)+19,1) | F24: =IF(B24="","",IF(B24<40,"Zona de risco",IF(B24<70,"Atenção","Blindado em construção")))
A25: =DATE(YEAR(Início!$B$6),MONTH(Início!$B$6)+20,1) | F25: =IF(B25="","",IF(B25<40,"Zona de risco",IF(B25<70,"Atenção","Blindado em construção")))
A26: =DATE(YEAR(Início!$B$6),MONTH(Início!$B$6)+21,1) | F26: =IF(B26="","",IF(B26<40,"Zona de risco",IF(B26<70,"Atenção","Blindado em construção")))
A27: =DATE(YEAR(Início!$B$6),MONTH(Início!$B$6)+22,1) | F27: =IF(B27="","",IF(B27<40,"Zona de risco",IF(B27<70,"Atenção","Blindado em construção")))
A28: =DATE(YEAR(Início!$B$6),MONTH(Início!$B$6)+23,1) | F28: =IF(B28="","",IF(B28<40,"Zona de risco",IF(B28<70,"Atenção","Blindado em construção")))

Sheet Calendário
A1: Calendário da reforma
A2: Datas oficiais e o que fazer · coluna 'Faltam' conta os dias
A4: Data | B4: Evento | C4: O que acontece | D4: O que fazer (Comércio) | E4: O que fazer (Serviços) | F4: O que fazer (Indústria/Agro/B2B) | G4: Faltam (dias)
A5: 46023 | B5: Ano de teste | C5: CBS (0,9%) e IBS (0,1%) aparecem destacados na nota fiscal para teste. Quem cumpre as obrigações da nota não paga esse valor a mais. | D5: Confira se o seu sistema de caixa/PDV já destaca CBS e IBS. | E5: Confira se a sua nota de serviço já sai no padrão novo. | F5: Confira se as NF-e já saem com os campos de CBS e IBS. | G5: =IF(A5<TODAY(),"já passou",A5-TODAY())
A6: 46310 | B6: Testes do split payment | C6: Começam os testes técnicos entre bancos/maquininhas e a plataforma pública. Ainda não mexem em pagamento real. | D6: Nada a pagar. Pergunte ao banco e à maquininha como vão tratar o split. | E6: Nada a pagar. Pergunte ao banco como vai funcionar. | F6: Comece a simular no fluxo de caixa o recebimento líquido (sem o imposto). | G6: =IF(A6<TODAY(),"já passou",A6-TODAY())
A7: 46325 | B7: Prazo: Simples pode escolher o "híbrido" para jan–jun/2027 | C7: Empresas do Simples podem optar por pagar IBS e CBS por fora do DAS (regime regular). Quem não optar continua "por dentro" e pode decidir de novo em março de 2027. | D7: Se vende quase tudo para consumidor final, em geral fica por dentro. Confirme com o contador. | E7: Se vende para empresas, peça ao contador a simulação dos dois cenários. | F7: Vende para empresas? Essa decisão afeta o crédito que o seu cliente aproveita. Simule com o contador. | G7: =IF(A7<TODAY(),"já passou",A7-TODAY())
A8: 46371 | B8: Senado fixa a alíquota da CBS para 2027 | C8: O TCU envia o cálculo até 30/10 e o Senado fixa a alíquota de referência até 15/12. Estimativa não oficial usada pelo Comitê Gestor: CBS 9,21% e IBS 18,7% (27,91% somados no modelo final). | D8: Atualize o simulador de preço com a alíquota oficial assim que sair. | E8: Atualize o simulador de preço com a alíquota oficial. | F8: Atualize preços e propostas de 2027 com a alíquota oficial. | G8: =IF(A8<TODAY(),"já passou",A8-TODAY())
A9: 46388 | B9: CBS entra no lugar de PIS e Cofins | C9: PIS e Cofins deixam de existir. O IPI vai a zero (exceto produtos da Zona Franca de Manaus). Começa o Imposto Seletivo (cigarro, bebidas alcoólicas e açucaradas, veículos, mineração etc.). O IBS fica em 0,1% em 2027 e 2028. | D9: Tabela de preços revisada e sistema pronto antes do dia 1º. | E9: Contratos e propostas com cláusula de reajuste tributário. | F9: Revise preço de venda, crédito nas compras e contratos com clientes. | G9: =IF(A9<TODAY(),"já passou",A9-TODAY())
A10: 46447 | B10: Janela do Simples: entrar ou sair do híbrido | C10: Optantes do Simples podem escolher (ou desistir) do regime regular de IBS/CBS, com efeito no 2º semestre de 2027. Depois, as janelas são em março e setembro de cada ano. | D10: Reveja a decisão com os números do 1º trimestre. | E10: Leve ao contador a simulação feita no painel. | F10: Pergunte aos seus maiores clientes como eles tratam o crédito de fornecedores do Simples. | G10: =IF(A10<TODAY(),"já passou",A10-TODAY())
A11: 46569 | B11: Split payment começa (gradual) | C11: Previsão de início gradual e facultativo, começando nas vendas entre empresas: o imposto é separado na hora do pagamento e você recebe o valor líquido. | D11: Pouco muda no balcão no começo, mas fornecedores podem mudar condições. | E11: Se atende empresas, prepare o caixa para receber o líquido. | F11: Fim do imposto como capital de giro: ajuste o fluxo de caixa e a reserva. | G11: =IF(A11<TODAY(),"já passou",A11-TODAY())
A12: 47119 | B12: Começa a troca de ICMS e ISS pelo IBS | C12: ICMS e ISS passam a 90% das alíquotas atuais; o IBS sobe na mesma proporção. | D12: Revise preços: o ICMS começa a cair e o IBS a subir. | E12: Revise preços: o ISS começa a cair e o IBS a subir. | F12: Benefícios de ICMS começam a ser reduzidos: reveja preços e contratos. | G12: =IF(A12<TODAY(),"já passou",A12-TODAY())
A13: 47484 | B13: ICMS e ISS a 80% | C13: Segue a transição: ICMS e ISS em 80% das alíquotas; IBS sobe. | D13: Revisão anual de preço. | E13: Revisão anual de preço. | F13: Revisão anual de preço e contratos. | G13: =IF(A13<TODAY(),"já passou",A13-TODAY())
A14: 47849 | B14: ICMS e ISS a 70% | C14: Segue a transição. | D14: Revisão anual de preço. | E14: Revisão anual de preço. | F14: Revisão anual de preço e contratos. | G14: =IF(A14<TODAY(),"já passou",A14-TODAY())
A15: 48214 | B15: ICMS e ISS a 60% | C15: Último ano da convivência dos dois sistemas. | D15: Prepare o sistema para o fim do ICMS. | E15: Prepare o sistema para o fim do ISS. | F15: Prepare o sistema para o fim do ICMS/ISS. | G15: =IF(A15<TODAY(),"já passou",A15-TODAY())
A16: 48580 | B16: Modelo novo completo | C16: ICMS e ISS deixam de existir. Ficam CBS (federal) e IBS (estados e municípios), com crédito amplo nas compras. A soma das alíquotas de referência não pode passar de 26,5% em 2033, pela regra da lei (com mecanismo de ajuste). | D16: Preço e margem já no modelo novo. | E16: Preço e margem já no modelo novo. | F16: Preço, crédito e contratos já no modelo novo. | G16: =IF(A16<TODAY(),"já passou",A16-TODAY())
A18: Fontes: EC 132/2023; LC 214/2025; Res. CGSN 194/2026; Receita Federal; Comsefaz; Senado. Dados de 28/10/2026.

Sheet Simples x Híbrido
A1: Simples: por dentro x híbrido
A2: Faça antes das janelas de março e setembro · valores do mês
A4: Dado | B4: Valor
A5: Faturamento do mês | B5: 40000
A6: Alíquota efetiva do DAS hoje | B6: 0.08
A7: Parte de IBS/CBS dentro do DAS (% da venda) — peça ao contador | B7: 0.03
A8: % das vendas para empresas | B8: 0.3
A9: Compras com nota de fornecedores do regime regular | B9: 12000
A10: Alíquota IBS+CBS (modelo final, estimativa) | B10: 0.2791
A11: Redução de alíquota do seu item (0, 30%, 60%) | B11: 0
A12: Custo extra de contabilidade/sistema no híbrido | B12: 300
A13: Alíquota efetiva no seu item | B13: =B10*(1-B11)
A15: Resultado | B15: Por dentro | C15: Híbrido | D15: Diferença
A16: Imposto do mês | B16: =B5*B6 | C16: =B5*(B6-B7)+B5/(1+B13)*B13-B9*B10/(1+B10)+B12 | D16: =C16-B16
A17: Crédito do cliente PJ a cada R$ 1.000 | B17: =1000*B7 | C17: =1000/(1+B13)*B13 | D17: =C17-B17
A18: Crédito gerado aos clientes PJ no mês | B18: =B5*B8*B7 | C18: =B5*B8/(1+B13)*B13 | D18: =C18-B18
A20: =IF(B8<0.2,"Você vende pouco para empresas: ficar POR DENTRO tende a ser o caminho. Confirme com o contador.",IF(D16<=0,"O híbrido sai mais barato e gera mais crédito ao cliente: avalie com o contador.","O híbrido custa mais imposto por mês (célula D16), mas gera mais crédito aos clientes PJ (célula D18). Vale se os clientes PJ pagariam mais ou deixariam de comprar de você por falta de crédito. Decida com o contador."))

Sheet Preço 2027
A1: Preço 2027 · item a item
A2: Regime regular (Presumido/Real/híbrido). Alíquotas editáveis nas células amarelas do topo.
A4: CBS (estimativa; oficial até 15/12/2026) | B4: 0.0921
A5: IBS final (estimativa) | B5: 0.187
A6: PIS/Cofins hoje (% da venda) | B6: 0.0365
A7: % das compras com crédito cheio | B7: 0.7
A9: Item | B9: Preço hoje | C9: Custo direto | D9: Impostos hoje % | E9: Taxas/comissão % | F9: Crédito hoje % (PIS+ICMS) | G9: Crédito ICMS hoje % | H9: Redução (0/0,3/0,6/1) | I9: Lucro hoje | J9: Preço 2027 p/ manter lucro | K9: Variação 2027 | L9: Preço 2033 p/ manter lucro | M9: Variação 2033
A10: Produto/serviço exemplo | B10: 100 | C10: 50 | D10: 0.12 | E10: 0.04 | F10: 0 | G10: 0 | H10: 0 | I10: =IF(B10="","",B10*(1-D10-E10)-C10+C10*F10*$B$7) | J10: =IF(B10="","",(I10+C10-(C10*$B$7*$B$4/(1+$B$4+MAX(0,D10-$B$6))+C10*$B$7*G10))/((1+($B$4*(1-H10)+IF(H10<1,0.001,0)))*(1-MAX(0,D10-$B$6)-E10)-($B$4*(1-H10)+IF(H10<1,0.001,0)))*(1+($B$4*(1-H10)+IF(H10<1,0.001,0)))) | K10: =IF(B10="","",J10/B10-1) | L10: =IF(B10="","",(I10+C10-(C10*$B$7*($B$4+$B$5)/(1+($B$4+$B$5))))/(1-E10*(1+(($B$4+$B$5)*(1-H10))))*(1+(($B$4+$B$5)*(1-H10)))) | M10: =IF(B10="","",L10/B10-1)
I11: =IF(B11="","",B11*(1-D11-E11)-C11+C11*F11*$B$7) | J11: =IF(B11="","",(I11+C11-(C11*$B$7*$B$4/(1+$B$4+MAX(0,D11-$B$6))+C11*$B$7*G11))/((1+($B$4*(1-H11)+IF(H11<1,0.001,0)))*(1-MAX(0,D11-$B$6)-E11)-($B$4*(1-H11)+IF(H11<1,0.001,0)))*(1+($B$4*(1-H11)+IF(H11<1,0.001,0)))) | K11: =IF(B11="","",J11/B11-1) | L11: =IF(B11="","",(I11+C11-(C11*$B$7*($B$4+$B$5)/(1+($B$4+$B$5))))/(1-E11*(1+(($B$4+$B$5)*(1-H11))))*(1+(($B$4+$B$5)*(1-H11)))) | M11: =IF(B11="","",L11/B11-1)
I12: =IF(B12="","",B12*(1-D12-E12)-C12+C12*F12*$B$7) | J12: =IF(B12="","",(I12+C12-(C12*$B$7*$B$4/(1+$B$4+MAX(0,D12-$B$6))+C12*$B$7*G12))/((1+($B$4*(1-H12)+IF(H12<1,0.001,0)))*(1-MAX(0,D12-$B$6)-E12)-($B$4*(1-H12)+IF(H12<1,0.001,0)))*(1+($B$4*(1-H12)+IF(H12<1,0.001,0)))) | K12: =IF(B12="","",J12/B12-1) | L12: =IF(B12="","",(I12+C12-(C12*$B$7*($B$4+$B$5)/(1+($B$4+$B$5))))/(1-E12*(1+(($B$4+$B$5)*(1-H12))))*(1+(($B$4+$B$5)*(1-H12)))) | M12: =IF(B12="","",L12/B12-1)
I13: =IF(B13="","",B13*(1-D13-E13)-C13+C13*F13*$B$7) | J13: =IF(B13="","",(I13+C13-(C13*$B$7*$B$4/(1+$B$4+MAX(0,D13-$B$6))+C13*$B$7*G13))/((1+($B$4*(1-H13)+IF(H13<1,0.001,0)))*(1-MAX(0,D13-$B$6)-E13)-($B$4*(1-H13)+IF(H13<1,0.001,0)))*(1+($B$4*(1-H13)+IF(H13<1,0.001,0)))) | K13: =IF(B13="","",J13/B13-1) | L13: =IF(B13="","",(I13+C13-(C13*$B$7*($B$4+$B$5)/(1+($B$4+$B$5))))/(1-E13*(1+(($B$4+$B$5)*(1-H13))))*(1+(($B$4+$B$5)*(1-H13)))) | M13: =IF(B13="","",L13/B13-1)
I14: =IF(B14="","",B14*(1-D14-E14)-C14+C14*F14*$B$7) | J14: =IF(B14="","",(I14+C14-(C14*$B$7*$B$4/(1+$B$4+MAX(0,D14-$B$6))+C14*$B$7*G14))/((1+($B$4*(1-H14)+IF(H14<1,0.001,0)))*(1-MAX(0,D14-$B$6)-E14)-($B$4*(1-H14)+IF(H14<1,0.001,0)))*(1+($B$4*(1-H14)+IF(H14<1,0.001,0)))) | K14: =IF(B14="","",J14/B14-1) | L14: =IF(B14="","",(I14+C14-(C14*$B$7*($B$4+$B$5)/(1+($B$4+$B$5))))/(1-E14*(1+(($B$4+$B$5)*(1-H14))))*(1+(($B$4+$B$5)*(1-H14)))) | M14: =IF(B14="","",L14/B14-1)
I15: =IF(B15="","",B15*(1-D15-E15)-C15+C15*F15*$B$7) | J15: =IF(B15="","",(I15+C15-(C15*$B$7*$B$4/(1+$B$4+MAX(0,D15-$B$6))+C15*$B$7*G15))/((1+($B$4*(1-H15)+IF(H15<1,0.001,0)))*(1-MAX(0,D15-$B$6)-E15)-($B$4*(1-H15)+IF(H15<1,0.001,0)))*(1+($B$4*(1-H15)+IF(H15<1,0.001,0)))) | K15: =IF(B15="","",J15/B15-1) | L15: =IF(B15="","",(I15+C15-(C15*$B$7*($B$4+$B$5)/(1+($B$4+$B$5))))/(1-E15*(1+(($B$4+$B$5)*(1-H15))))*(1+(($B$4+$B$5)*(1-H15)))) | M15: =IF(B15="","",L15/B15-1)
I16: =IF(B16="","",B16*(1-D16-E16)-C16+C16*F16*$B$7) | J16: =IF(B16="","",(I16+C16-(C16*$B$7*$B$4/(1+$B$4+MAX(0,D16-$B$6))+C16*$B$7*G16))/((1+($B$4*(1-H16)+IF(H16<1,0.001,0)))*(1-MAX(0,D16-$B$6)-E16)-($B$4*(1-H16)+IF(H16<1,0.001,0)))*(1+($B$4*(1-H16)+IF(H16<1,0.001,0)))) | K16: =IF(B16="","",J16/B16-1) | L16: =IF(B16="","",(I16+C16-(C16*$B$7*($B$4+$B$5)/(1+($B$4+$B$5))))/(1-E16*(1+(($B$4+$B$5)*(1-H16))))*(1+(($B$4+$B$5)*(1-H16)))) | M16: =IF(B16="","",L16/B16-1)
I17: =IF(B17="","",B17*(1-D17-E17)-C17+C17*F17*$B$7) | J17: =IF(B17="","",(I17+C17-(C17*$B$7*$B$4/(1+$B$4+MAX(0,D17-$B$6))+C17*$B$7*G17))/((1+($B$4*(1-H17)+IF(H17<1,0.001,0)))*(1-MAX(0,D17-$B$6)-E17)-($B$4*(1-H17)+IF(H17<1,0.001,0)))*(1+($B$4*(1-H17)+IF(H17<1,0.001,0)))) | K17: =IF(B17="","",J17/B17-1) | L17: =IF(B17="","",(I17+C17-(C17*$B$7*($B$4+$B$5)/(1+($B$4+$B$5))))/(1-E17*(1+(($B$4+$B$5)*(1-H17))))*(1+(($B$4+$B$5)*(1-H17)))) | M17: =IF(B17="","",L17/B17-1)
I18: =IF(B18="","",B18*(1-D18-E18)-C18+C18*F18*$B$7) | J18: =IF(B18="","",(I18+C18-(C18*$B$7*$B$4/(1+$B$4+MAX(0,D18-$B$6))+C18*$B$7*G18))/((1+($B$4*(1-H18)+IF(H18<1,0.001,0)))*(1-MAX(0,D18-$B$6)-E18)-($B$4*(1-H18)+IF(H18<1,0.001,0)))*(1+($B$4*(1-H18)+IF(H18<1,0.001,0)))) | K18: =IF(B18="","",J18/B18-1) | L18: =IF(B18="","",(I18+C18-(C18*$B$7*($B$4+$B$5)/(1+($B$4+$B$5))))/(1-E18*(1+(($B$4+$B$5)*(1-H18))))*(1+(($B$4+$B$5)*(1-H18)))) | M18: =IF(B18="","",L18/B18-1)
I19: =IF(B19="","",B19*(1-D19-E19)-C19+C19*F19*$B$7) | J19: =IF(B19="","",(I19+C19-(C19*$B$7*$B$4/(1+$B$4+MAX(0,D19-$B$6))+C19*$B$7*G19))/((1+($B$4*(1-H19)+IF(H19<1,0.001,0)))*(1-MAX(0,D19-$B$6)-E19)-($B$4*(1-H19)+IF(H19<1,0.001,0)))*(1+($B$4*(1-H19)+IF(H19<1,0.001,0)))) | K19: =IF(B19="","",J19/B19-1) | L19: =IF(B19="","",(I19+C19-(C19*$B$7*($B$4+$B$5)/(1+($B$4+$B$5))))/(1-E19*(1+(($B$4+$B$5)*(1-H19))))*(1+(($B$4+$B$5)*(1-H19)))) | M19: =IF(B19="","",L19/B19-1)
I20: =IF(B20="","",B20*(1-D20-E20)-C20+C20*F20*$B$7) | J20: =IF(B20="","",(I20+C20-(C20*$B$7*$B$4/(1+$B$4+MAX(0,D20-$B$6))+C20*$B$7*G20))/((1+($B$4*(1-H20)+IF(H20<1,0.001,0)))*(1-MAX(0,D20-$B$6)-E20)-($B$4*(1-H20)+IF(H20<1,0.001,0)))*(1+($B$4*(1-H20)+IF(H20<1,0.001,0)))) | K20: =IF(B20="","",J20/B20-1) | L20: =IF(B20="","",(I20+C20-(C20*$B$7*($B$4+$B$5)/(1+($B$4+$B$5))))/(1-E20*(1+(($B$4+$B$5)*(1-H20))))*(1+(($B$4+$B$5)*(1-H20)))) | M20: =IF(B20="","",L20/B20-1)
I21: =IF(B21="","",B21*(1-D21-E21)-C21+C21*F21*$B$7) | J21: =IF(B21="","",(I21+C21-(C21*$B$7*$B$4/(1+$B$4+MAX(0,D21-$B$6))+C21*$B$7*G21))/((1+($B$4*(1-H21)+IF(H21<1,0.001,0)))*(1-MAX(0,D21-$B$6)-E21)-($B$4*(1-H21)+IF(H21<1,0.001,0)))*(1+($B$4*(1-H21)+IF(H21<1,0.001,0)))) | K21: =IF(B21="","",J21/B21-1) | L21: =IF(B21="","",(I21+C21-(C21*$B$7*($B$4+$B$5)/(1+($B$4+$B$5))))/(1-E21*(1+(($B$4+$B$5)*(1-H21))))*(1+(($B$4+$B$5)*(1-H21)))) | M21: =IF(B21="","",L21/B21-1)
I22: =IF(B22="","",B22*(1-D22-E22)-C22+C22*F22*$B$7) | J22: =IF(B22="","",(I22+C22-(C22*$B$7*$B$4/(1+$B$4+MAX(0,D22-$B$6))+C22*$B$7*G22))/((1+($B$4*(1-H22)+IF(H22<1,0.001,0)))*(1-MAX(0,D22-$B$6)-E22)-($B$4*(1-H22)+IF(H22<1,0.001,0)))*(1+($B$4*(1-H22)+IF(H22<1,0.001,0)))) | K22: =IF(B22="","",J22/B22-1) | L22: =IF(B22="","",(I22+C22-(C22*$B$7*($B$4+$B$5)/(1+($B$4+$B$5))))/(1-E22*(1+(($B$4+$B$5)*(1-H22))))*(1+(($B$4+$B$5)*(1-H22)))) | M22: =IF(B22="","",L22/B22-1)
... I24: =IF(B24="","",B24*(1-D24-E24)-C24+C24*F24*$B$7) | J24: =IF(B24="","",(I24+C24-(C24*$B$7*$B$4/(1+$B$4+MAX(0,D24-$B$6))+C24*$B$7*G24))/((1+($B$4*(1-H24)+IF(H24<1,0.001,0)))*(1-MAX(0,D24-$B$6)-E24)-($B$4*(1-H24)+IF(H24<1,0.001,0)))*(1+($B$4*(1-H24)+IF(H24<1,0.001,0)))) | K24: =IF(B24="","",J24/B24-1) | L24: =IF(B24="","",(I24+C24-(C24*$B$7*($B$4+$B$5)/(1+($B$4+$B$5))))/(1-E24*(1+(($B$4+$B$5)*(1-H24))))*(1+(($B$4+$B$5)*(1-H24)))) | M24: =IF(B24="","",L24/B24-1)
A26: Preço 2027/2033 já inclui o IBS/CBS 'por fora'. Estimativa educativa: confirme com o contador. Mesma conta do simulador Preço 2027 do app.
